MANIFEST.in
README.rst
setup.py
collective/__init__.py
collective.contentrules.subscription.egg-info/PKG-INFO
collective.contentrules.subscription.egg-info/SOURCES.txt
collective.contentrules.subscription.egg-info/dependency_links.txt
collective.contentrules.subscription.egg-info/entry_points.txt
collective.contentrules.subscription.egg-info/namespace_packages.txt
collective.contentrules.subscription.egg-info/not-zip-safe
collective.contentrules.subscription.egg-info/requires.txt
collective.contentrules.subscription.egg-info/top_level.txt
collective/contentrules/__init__.py
collective/contentrules/subscription/TODO.txt
collective/contentrules/subscription/__init__.py
collective/contentrules/subscription/configure.zcml
collective/contentrules/subscription/i18n.sh
collective/contentrules/subscription/testing.py
collective/contentrules/subscription/tool.py
collective/contentrules/subscription/vocabularies.py
collective/contentrules/subscription/Extensions/install.py
collective/contentrules/subscription/actions/__init__.py
collective/contentrules/subscription/actions/configure.zcml
collective/contentrules/subscription/actions/mail.py
collective/contentrules/subscription/actions/templates/mail.pt
collective/contentrules/subscription/browser/__init__.py
collective/contentrules/subscription/browser/configure.zcml
collective/contentrules/subscription/browser/contentrules_subscription.css
collective/contentrules/subscription/browser/controlpanel.pt
collective/contentrules/subscription/browser/controlpanel.py
collective/contentrules/subscription/browser/interfaces.py
collective/contentrules/subscription/browser/notify_subscribe.py
collective/contentrules/subscription/locales/collective.contentrules.subscription.pot
collective/contentrules/subscription/locales/manual.pot
collective/contentrules/subscription/locales/it/LC_MESSAGES/collective.contentrules.subscription.po
collective/contentrules/subscription/profiles/default/browserlayer.xml
collective/contentrules/subscription/profiles/default/controlpanel.xml
collective/contentrules/subscription/profiles/default/cssregistry.xml
collective/contentrules/subscription/profiles/default/metadata.xml
collective/contentrules/subscription/profiles/default/toolset.xml
collective/contentrules/subscription/profiles/uninstall/browserlayer.xml
collective/contentrules/subscription/profiles/uninstall/controlpanel.xml
collective/contentrules/subscription/profiles/uninstall/cssregistry.xml
