Metadata-Version: 1.1
Name: collective.contentrules.subscription
Version: 0.1.0
Summary: A Plone content rule for send e-mail to addresses taken from a subscription list
Home-page: http://plone.org/products/collective.contentrules.subscription
Author: RedTurtle Technology
Author-email: sviluppoplone@redturtle.it
License: GPL
Keywords: plone rules mail
Platform: UNKNOWN
Classifier: Framework :: Plone
Classifier: Framework :: Plone :: 4.0
Classifier: Framework :: Plone :: 4.1
Classifier: Framework :: Plone :: 4.2
Classifier: Framework :: Plone :: 4.3
Classifier: Programming Language :: Python
Classifier: Development Status :: 4 - Beta
Classifier: Topic :: Communications :: Email
Classifier: License :: OSI Approved :: GNU General Public License (GPL)
